nr_oaipmh_harvesters/config.py
nr_oaipmh_harvesters/ext.py
nr_oaipmh_harvesters/nusl/__init__.py
nr_oaipmh_harvesters/nusl/temp_institutions.py
nr_oaipmh_harvesters/nusl/transformer.py
nr_oaipmh_harvesters-1.0.71.dist-info/METADATA
nr_oaipmh_harvesters-1.0.71.dist-info/WHEEL
nr_oaipmh_harvesters-1.0.71.dist-info/entry_points.txt
nr_oaipmh_harvesters-1.0.71.dist-info/top_level.txt
nr_oaipmh_harvesters-1.0.71.dist-info/RECORD
