Metadata-Version: 2.4
Name: nr-oaipmh-harvesters
Version: 1.0.71
Summary: OAIPMH harvesters for National repository
Requires-Dist: oarepo-oai-pmh-harvester>=4.0.0
Requires-Dist: dojson
Requires-Dist: Levenshtein
Requires-Dist: nr-metadata
